{
  "createdAt": "2020-09-06T07:46:50.692Z",
  "id": 236,
  "title": "sit error et odio placeat",
  "subtitle": "accusantium praesentium iure cumque at aspernatur minima necessitatibus amet incidunt consectetur ipsum",
  "content": "Rerum soluta quia expedita blanditiis architecto. Veritatis nulla quisquam alias. Consequuntur cum voluptatum soluta accusantium autem laborum suscipit rerum.\nRepudiandae similique sunt eum itaque hic dolorem. Recusandae magnam voluptatum commodi tenetur voluptas natus eligendi. Voluptatum tenetur perferendis reiciendis.\nVoluptatem eius porro molestiae rem soluta eos quis. Earum similique repudiandae. Dolore soluta autem cupiditate iure voluptatem maxime distinctio ratione.\nIusto dolor autem enim officia aliquam odio. Doloremque molestias adipisci. Omnis non porro iusto a laborum quibusdam.\nRerum voluptatibus qui odit quos provident earum. Voluptatum rem nam. Sint voluptatem eaque."
}